{
    "group_name": "xenforge_replyalerter",
    "title": "Checkbox container style",
    "description": "Define checkbox container style",
    "property_type": "css",
    "css_components": [
        "text",
        "background",
        "border",
        "border_radius",
        "border_width_simple",
        "border_color_simple",
        "border_radius_simple",
        "padding",
        "extra"
    ],
    "value_type": "",
    "value_parameters": "",
    "depends_on": "",
    "value_group": "",
    "property_value": {
        "padding-top": "3px"
    },
    "display_order": 20
}